{"type":"footer","name":"Footer group","sections":{"footer":{"type":"footer","blocks":{"newsletter_33BPAY":{"type":"newsletter","settings":{"title":"","content":"<p>Make life healthier for your dog with Regev. Sign up here for updates!<\/p>","button_background":"","button_text_color":""}},"links_jYna93":{"type":"links","settings":{"menu":"customer-service","show_menu_title":true,"menu_title":""}},"text_hFAETL":{"type":"text","settings":{"title":"About Regev","content":"<p>Providing your dog with the care they deserve, one wellness gummy at a time for a happier life.<\/p>","enable_follow_on_shop":false}}},"block_order":["newsletter_33BPAY","links_jYna93","text_hFAETL"],"custom_css":[],"settings":{"color_scheme":"scheme-3","separate_section_with_border":false,"show_social_media":true,"show_payment_icons":true,"show_country_selector":true,"show_country_name":true,"show_country_flag":true,"show_locale_selector":false}}},"order":["footer"]}